nsenter/__init__.py
nsenter-0.2.dist-info/DESCRIPTION.rst
nsenter-0.2.dist-info/METADATA
nsenter-0.2.dist-info/RECORD
nsenter-0.2.dist-info/WHEEL
nsenter-0.2.dist-info/entry_points.txt
nsenter-0.2.dist-info/metadata.json
nsenter-0.2.dist-info/top_level.txt
